AUTHORS
CHANGES
LICENSE
MANIFEST.in
README.dialects.rst
README.rst
README.unittests.rst
pyproject.toml
setup.cfg
setup.py
tox.ini
doc/build/Makefile
doc/build/conf.py
doc/build/contents.rst
doc/build/copyright.rst
doc/build/errors.rst
doc/build/glossary.rst
doc/build/index.rst
doc/build/intro.rst
doc/build/requirements.txt
doc/build/sqla_arch_small.png
doc/build/changelog/README.txt
doc/build/changelog/changelog_01.rst
doc/build/changelog/changelog_02.rst
doc/build/changelog/changelog_03.rst
doc/build/changelog/changelog_04.rst
doc/build/changelog/changelog_05.rst
doc/build/changelog/changelog_06.rst
doc/build/changelog/changelog_07.rst
doc/build/changelog/changelog_08.rst
doc/build/changelog/changelog_09.rst
doc/build/changelog/changelog_10.rst
doc/build/changelog/changelog_11.rst
doc/build/changelog/changelog_12.rst
doc/build/changelog/changelog_13.rst
doc/build/changelog/changelog_14.rst
doc/build/changelog/changelog_20.rst
doc/build/changelog/index.rst
doc/build/changelog/migration_04.rst
doc/build/changelog/migration_05.rst
doc/build/changelog/migration_06.rst
doc/build/changelog/migration_07.rst
doc/build/changelog/migration_08.rst
doc/build/changelog/migration_09.rst
doc/build/changelog/migration_10.rst
doc/build/changelog/migration_11.rst
doc/build/changelog/migration_12.rst
doc/build/changelog/migration_13.rst
doc/build/changelog/migration_14.rst
doc/build/changelog/migration_20.rst
doc/build/changelog/unreleased_11/README.txt
doc/build/changelog/unreleased_12/README.txt
doc/build/changelog/unreleased_13/6135.rst
doc/build/changelog/unreleased_13/6182.rst
doc/build/changelog/unreleased_13/6392.rst
doc/build/changelog/unreleased_13/6589.rst
doc/build/changelog/unreleased_13/7115.rst
doc/build/changelog/unreleased_13/README.txt
doc/build/changelog/unreleased_14/7243.rst
doc/build/changelog/unreleased_14/7518.rst
doc/build/changelog/unreleased_14/7524.rst
doc/build/changelog/unreleased_14/7590.rst
doc/build/changelog/unreleased_14/7591.rst
lib/saorm14.egg-info/PKG-INFO
lib/saorm14.egg-info/SOURCES.txt
lib/saorm14.egg-info/dependency_links.txt
lib/saorm14.egg-info/requires.txt
lib/saorm14.egg-info/top_level.txt
