Metadata-Version: 2.1
Name: saorm14
Version: 1.0.dev0
Summary: Database Abstraction Library
Home-page: https://www.sqlalchemy.org
Author: Mike Bayer
Author-email: mike_mp@zzzcomputing.com
License: MIT
Project-URL: Documentation, https://docs.sqlalchemy.org
Project-URL: Issue Tracker, https://github.com/sqlalchemy/sqlalchemy/
Platform: UNKNOWN
Classifier: Development Status :: 5 - Production/Stable
Classifier: Intended Audience :: Developers
Classifier: License :: OSI Approved :: MIT License
Classifier: Operating System :: OS Independent
Classifier: Programming Language :: Python
Classifier: Programming Language :: Python :: 3
Classifier: Programming Language :: Python :: 3.7
Classifier: Programming Language :: Python :: 3.8
Classifier: Programming Language :: Python :: 3.9
Classifier: Programming Language :: Python :: 3.10
Classifier: Programming Language :: Python :: Implementation :: CPython
Classifier: Programming Language :: Python :: Implementation :: PyPy
Classifier: Topic :: Database :: Front-Ends
Requires-Python: >=3.7
Provides-Extra: asyncio
Provides-Extra: mypy
Provides-Extra: mssql
Provides-Extra: mssql_pymssql
Provides-Extra: mssql_pyodbc
Provides-Extra: mysql
Provides-Extra: mysql_connector
Provides-Extra: mariadb_connector
Provides-Extra: oracle
Provides-Extra: postgresql
Provides-Extra: postgresql_pg8000
Provides-Extra: postgresql_asyncpg
Provides-Extra: postgresql_psycopg2binary
Provides-Extra: postgresql_psycopg2cffi
Provides-Extra: postgresql_psycopg
Provides-Extra: pymysql
Provides-Extra: aiomysql
Provides-Extra: asyncmy
Provides-Extra: aiosqlite
Provides-Extra: sqlcipher
License-File: LICENSE
